{
  "name": "充能",
  "icon": "minecraft:clock",
  "category": "victus:basics",
  "pages": [
    {
      "type": "patchouli:text",
      "text": "破碎的红心要素在充能后才会重新生效。充能的过程是从左到右依次进行的，你可以通过生命条上的$(thing)金质边框$()来辨别——这些边框覆盖了所有已镶嵌红心要素的红心；只要$(o)任何$()要素尚未完全充能，它们就会显现。"
    },
    {
      "type": "patchouli:text",
      "text": "在设计你的要素方案时要记住，一个正在充能的红心要素会$(l)完全$()阻止其右侧的其它要素的充能——这通常意味着，你应该避免把充能时间特别长的红心要素镶嵌在生命条的左侧。$(p)你可以在各个红心要素的$(thing)提示文本$()中找到其充能时间。$(p)如果你觉得红心要素的充能太慢，$(thing)苏心药水$()应该会有所助益。"
    }
  ]
}